{
  "id": "182",
  "name": "Webster Hall",
  "city": "New York",
  "state": "NY",
  "concert_count": 4,
  "concerts": [
    {
      "id": "1225",
      "show_number": 1224,
      "date": "2024-12-12",
      "festival_name": null,
      "artists": "Kip Moore"
    },
    {
      "id": "696",
      "show_number": 695,
      "date": "2016-06-10",
      "festival_name": null,
      "artists": "Mudcrutch"
    },
    {
      "id": "525",
      "show_number": 524,
      "date": "2012-10-18",
      "festival_name": null,
      "artists": "Ryan Bingham"
    },
    {
      "id": "293",
      "show_number": 292,
      "date": "2007-03-14",
      "festival_name": null,
      "artists": "Fab Faux"
    }
  ]
}