{
  "id": "180",
  "name": "Dwight Yoakam",
  "concert_count": 2,
  "top_songs": [
    {
      "name": "The Outsiders",
      "times_played": 2
    },
    {
      "name": "Creepin'",
      "times_played": 2
    },
    {
      "name": "Guys Like Me",
      "times_played": 2
    },
    {
      "name": "Carolina",
      "times_played": 2
    },
    {
      "name": "I'm Gettin' Stoned",
      "times_played": 2
    },
    {
      "name": "Talladega",
      "times_played": 2
    },
    {
      "name": "Pledge Allegiance to the Hag",
      "times_played": 2
    },
    {
      "name": "Drink in My Hand",
      "times_played": 2
    },
    {
      "name": "The Hard Way",
      "times_played": 2
    },
    {
      "name": "Jack Daniels",
      "times_played": 2
    }
  ],
  "concerts": [
    {
      "id": "959",
      "show_number": 958,
      "date": "2019-11-09",
      "festival_name": null,
      "venue": "Terminal 5",
      "city": "New York",
      "state": "NY",
      "has_setlist": true,
      "opening_song": null,
      "closing_song": null
    },
    {
      "id": "605",
      "show_number": 604,
      "date": "2014-10-17",
      "festival_name": "Multi-Artist Show",
      "venue": "Madison Square Garden",
      "city": "New York",
      "state": "NY",
      "has_setlist": true,
      "opening_song": null,
      "closing_song": null
    }
  ]
}