{
  "id": "212",
  "name": "Fleetwood Mac",
  "concert_count": 5,
  "top_songs": [
    {
      "name": "The Chain",
      "times_played": 3
    },
    {
      "name": "Gypsy",
      "times_played": 3
    },
    {
      "name": "Little Lies",
      "times_played": 3
    },
    {
      "name": "Go Your Own Way",
      "times_played": 3
    },
    {
      "name": "You Make Loving Fun",
      "times_played": 2
    },
    {
      "name": "Dreams",
      "times_played": 2
    },
    {
      "name": "Second Hand News",
      "times_played": 2
    },
    {
      "name": "Rhiannon",
      "times_played": 2
    },
    {
      "name": "Everywhere",
      "times_played": 2
    },
    {
      "name": "Say You Love Me",
      "times_played": 2
    }
  ],
  "concerts": [
    {
      "id": "900",
      "show_number": 899,
      "date": "2019-03-11",
      "festival_name": null,
      "venue": "Madison Square Garden",
      "city": "New York",
      "state": "NY",
      "has_setlist": false,
      "opening_song": null,
      "closing_song": null
    },
    {
      "id": "603",
      "show_number": 602,
      "date": "2014-10-09",
      "festival_name": null,
      "venue": "Today Show Plaza at Rockefeller Center",
      "city": "New York",
      "state": "NY",
      "has_setlist": false,
      "opening_song": null,
      "closing_song": null
    },
    {
      "id": "602",
      "show_number": 601,
      "date": "2014-10-07",
      "festival_name": null,
      "venue": "Madison Square Garden",
      "city": "New York",
      "state": "NY",
      "has_setlist": false,
      "opening_song": null,
      "closing_song": null
    },
    {
      "id": "384",
      "show_number": 383,
      "date": "2009-06-11",
      "festival_name": null,
      "venue": "Madison Square Garden",
      "city": "New York",
      "state": "NY",
      "has_setlist": false,
      "opening_song": null,
      "closing_song": null
    },
    {
      "id": "194",
      "show_number": 193,
      "date": "2003-09-30",
      "festival_name": null,
      "venue": "Madison Square Garden",
      "city": "New York",
      "state": "NY",
      "has_setlist": false,
      "opening_song": null,
      "closing_song": null
    }
  ]
}