{
  "id": "251",
  "name": "Hot Tuna",
  "concert_count": 1,
  "top_songs": [
    {
      "name": "I Know You Rider",
      "times_played": 1
    },
    {
      "name": "I See the Light",
      "times_played": 1
    },
    {
      "name": "Bankrobber",
      "times_played": 1
    },
    {
      "name": "99 Year Blues",
      "times_played": 1
    },
    {
      "name": "Parchman Farm",
      "times_played": 1
    },
    {
      "name": "Hit Single #1",
      "times_played": 1
    },
    {
      "name": "I Can't Be Satisfied",
      "times_played": 1
    },
    {
      "name": "Ode for Billy Dean",
      "times_played": 1
    },
    {
      "name": "Going Down the Road Feeling Bad",
      "times_played": 1
    }
  ],
  "concerts": [
    {
      "id": "114",
      "show_number": 113,
      "date": "2000-08-04",
      "festival_name": "Multi-Artist Show",
      "venue": "Jones Beach Theater",
      "city": "Wantagh",
      "state": "NY",
      "has_setlist": true
    }
  ]
}