{
  "id": "422",
  "name": "Pearl Jam",
  "concert_count": 13,
  "top_songs": [
    {
      "name": "Alive",
      "times_played": 13
    },
    {
      "name": "Even Flow",
      "times_played": 12
    },
    {
      "name": "Do the Evolution",
      "times_played": 12
    },
    {
      "name": "Given to Fly",
      "times_played": 10
    },
    {
      "name": "Corduroy",
      "times_played": 10
    },
    {
      "name": "Better Man",
      "times_played": 9
    },
    {
      "name": "Porch",
      "times_played": 9
    },
    {
      "name": "Black",
      "times_played": 8
    },
    {
      "name": "Elderly Woman Behind the Counter in a Small Town",
      "times_played": 7
    },
    {
      "name": "Present Tense",
      "times_played": 7
    }
  ],
  "concerts": [
    {
      "id": "1194",
      "show_number": 1193,
      "date": "2024-09-12",
      "festival_name": null,
      "venue": "CFG Bank Arena",
      "city": "Baltimore",
      "state": "MD",
      "has_setlist": true
    },
    {
      "id": "1193",
      "show_number": 1192,
      "date": "2024-09-04",
      "festival_name": null,
      "venue": "Madison Square Garden",
      "city": "New York",
      "state": "NY",
      "has_setlist": true
    },
    {
      "id": "1192",
      "show_number": 1191,
      "date": "2024-09-03",
      "festival_name": null,
      "venue": "Madison Square Garden",
      "city": "New York",
      "state": "NY",
      "has_setlist": true
    },
    {
      "id": "1055",
      "show_number": 1054,
      "date": "2022-09-11",
      "festival_name": null,
      "venue": "Madison Square Garden",
      "city": "New York",
      "state": "NY",
      "has_setlist": true
    },
    {
      "id": "858",
      "show_number": 857,
      "date": "2018-09-02",
      "festival_name": null,
      "venue": "Fenway Park",
      "city": "Boston",
      "state": "MA",
      "has_setlist": true
    },
    {
      "id": "691",
      "show_number": 690,
      "date": "2016-05-02",
      "festival_name": null,
      "venue": "Madison Square Garden",
      "city": "New York",
      "state": "NY",
      "has_setlist": true
    },
    {
      "id": "690",
      "show_number": 689,
      "date": "2016-05-01",
      "festival_name": null,
      "venue": "Madison Square Garden",
      "city": "New York",
      "state": "NY",
      "has_setlist": true
    },
    {
      "id": "554",
      "show_number": 553,
      "date": "2013-10-19",
      "festival_name": null,
      "venue": "Barclays Center",
      "city": "Brooklyn",
      "state": "NY",
      "has_setlist": true
    },
    {
      "id": "421",
      "show_number": 420,
      "date": "2010-05-21",
      "festival_name": null,
      "venue": "Madison Square Garden",
      "city": "New York",
      "state": "NY",
      "has_setlist": true
    },
    {
      "id": "345",
      "show_number": 344,
      "date": "2008-06-25",
      "festival_name": null,
      "venue": "Madison Square Garden",
      "city": "New York",
      "state": "NY",
      "has_setlist": true
    },
    {
      "id": "262",
      "show_number": 261,
      "date": "2006-06-03",
      "festival_name": null,
      "venue": "Continental Airlines Arena",
      "city": "East Rutherford",
      "state": "NJ",
      "has_setlist": true
    },
    {
      "id": "180",
      "show_number": 179,
      "date": "2003-04-30",
      "festival_name": null,
      "venue": "Nassau Coliseum",
      "city": "Uniondale",
      "state": "NY",
      "has_setlist": true
    },
    {
      "id": "71",
      "show_number": 70,
      "date": "1998-09-10",
      "festival_name": null,
      "venue": "Madison Square Garden",
      "city": "New York",
      "state": "NY",
      "has_setlist": true
    }
  ]
}