{
  "id": "425",
  "name": "Peter Gabriel",
  "concert_count": 3,
  "top_songs": [],
  "concerts": [
    {
      "id": "1118",
      "show_number": 1117,
      "date": "2023-09-18",
      "festival_name": null,
      "venue": "Madison Square Garden",
      "city": "New York",
      "state": "NY",
      "has_setlist": false,
      "opening_song": null,
      "closing_song": null
    },
    {
      "id": "572",
      "show_number": 571,
      "date": "2014-04-10",
      "festival_name": "Multi-Artist Show",
      "venue": "Barclays Center",
      "city": "Brooklyn",
      "state": "NY",
      "has_setlist": false,
      "opening_song": null,
      "closing_song": null
    },
    {
      "id": "419",
      "show_number": 418,
      "date": "2010-05-03",
      "festival_name": null,
      "venue": "Radio City Music Hall",
      "city": "New York",
      "state": "NY",
      "has_setlist": false,
      "opening_song": null,
      "closing_song": null
    }
  ]
}