{
  "id": "500",
  "name": "Santana",
  "concert_count": 3,
  "top_songs": [],
  "concerts": [
    {
      "id": "1126",
      "show_number": 1125,
      "date": "2023-11-05",
      "festival_name": null,
      "venue": "House of Blues",
      "city": "Las Vegas",
      "state": "NV",
      "has_setlist": false,
      "opening_song": null,
      "closing_song": null
    },
    {
      "id": "85",
      "show_number": 84,
      "date": "1999-05-26",
      "festival_name": "Multi-Artist Show",
      "venue": "Giants Stadium",
      "city": "East Rutherford",
      "state": "NJ",
      "has_setlist": false,
      "opening_song": null,
      "closing_song": null
    },
    {
      "id": "44",
      "show_number": 43,
      "date": "1997-07-10",
      "festival_name": "Multi-Artist Show",
      "venue": "Thunder Ridge Ski Area",
      "city": "Patterson",
      "state": "NY",
      "has_setlist": false,
      "opening_song": null,
      "closing_song": null
    }
  ]
}